vennsketch/__init__.py
vennsketch/vennsketch.py
vennsketch-0.1.0.dist-info/LICENSE
vennsketch-0.1.0.dist-info/METADATA
vennsketch-0.1.0.dist-info/WHEEL
vennsketch-0.1.0.dist-info/top_level.txt
vennsketch-0.1.0.dist-info/RECORD
