Metadata-Version: 2.1
Name: vennsketch
Version: 0.1.0
Summary: Tool for creating a small sketch that can be used to check the intersection between sets in a time saving and secure way
Home-page: https://github.com/dave31415/vennsketch
Download-URL: https://pypi.org/project/vennsketch/
Author: David Johnston
Author-email: dave31415@gmail.com
License: MIT
Keywords: machine learning
Platform: UNKNOWN
License-File: LICENSE
